<character value="东">
	<introduce>
		<pinyin value="dong1" writing="dōng" />
		<bushou value="一" />
		<bushoustroke value="1" />
		<stroke value="5" />
		<order value="横折竖撇捺" />
	</introduce>
	<pron value="dōng">
		<sense tag="名" vernacular="东方；东边">
			<exam article="《木兰诗》" ref="东市买骏马，西市买鞍鞯，南市买辔头，北市买长鞭。" />
			<exam article="《捕蛇者说》" ref="悍吏之来吾乡，叫器乎东西，隳突乎南北。" />
		</sense>
		<sense tag="动" vernacular="向东；朝东">
			<exam article="《望洋兴叹》" ref="东西而视，不见水端。" />
			<exam article="《过秦论》" ref="南取汉中，西举巴蜀，东割膏腴之地，北取要害之郡。" />
		</sense>
		<sense tag="名" vernacular="主人">
			<exam article="《礼记·曲礼》有“主人就东阶，客就西阶。”之说，以后遂称主人为东。《红楼梦》" ref="况且你都拿出来做这个东也不够。" />
		</sense>
	</pron>
	<phrase value="东床">
		<sense value="指女婿" />
	</phrase>
	<phrase value="东第">
		<sense value="王公贵族所居的府第" />
	</phrase>
	<phrase value="东宫">
		<sense value="太子居住的地方" />
		<sense value="又指太子" />
	</phrase>
	<phrase value="东君">
		<sense value="日神" />
		<sense value="春神" />
		<sense value="东王公" />
	</phrase>
	<phrase value="东隅">
		<sense value="东方日出之处，指早晨" />
	</phrase>
</character>
