<character value="俸">
	<introduce>
		<pinyin value="feng4" writing="fèng" />
		<bushou value="亻" />
		<bushoustroke value="2" />
		<stroke value="10" />
		<order value="撇竖横横横撇捺横横竖" />
	</introduce>
	<pron value="fèng">
		<sense tag="名" vernacular="俸禄，旧时官吏的薪金">
			<exam article="《训俭示康》" ref="吾今日之俸岂能常有？" />
		</sense>
		<sense tag="名" vernacular="旧时指官吏任职的年限和资历">
			<exam article="《清史稿·选举志》" ref="官吏论俸序迁曰推升，不俟满挝秩曰即升。" />
		</sense>
	</pron>
	<phrase value="俸恤">
		<sense value="官吏除俸禄外，另给照顾亲属的钱米" />
	</phrase>
</character>
