<character value="叆">
	<introduce>
		<pinyin value="ai4" writing="ài" />
		<bushou value="厶" />
		<bushoustroke value="2" />
		<stroke value="14" />
		<order value="横横折捺撇捺捺撇捺折横撇折捺" />
	</introduce>
	<pron value="ài">
		<sense tag="形" vernacular="浓云密布">
			<exam article="《和徐生假山》" ref="叆若气融结，突如鬼镌镵。" />
		</sense>
		<sense tag="形" vernacular="香烟缭绕">
			<exam article="《满庭芳》" ref="香叆雕盘寒生冰筯。" />
		</sense>
	</pron>
	<phrase value="叆叆">
		<sense value="àiài浓重；茂密" />
	</phrase>
	<phrase value="叆叇">
		<sense value="yǐdài1" />
		<sense value="云多的样子" />
	</phrase>
	<phrase value="叆霼">
		<sense value="yǐxì依稀，不明的样子" />
	</phrase>
</character>
