<character value="异">
	<introduce>
		<pinyin value="yi4" writing="yì" />
		<bushou value="廾" />
		<bushoustroke value="3" />
		<stroke value="6" />
		<order value="折横折横撇竖" />
	</introduce>
	<pron value="yì">
		<sense tag="动" vernacular="分；分开">
			<exam article="《项脊轩志》" ref="迨诸父异爨，内外多置小门。" />
		</sense>
		<sense tag="形" vernacular="差别；不同">
			<exam article="《寡人之于国也》" ref="是何异于刺人而杀之，曰‘非我也，兵也’？" />
		</sense>
		<sense tag="形" vernacular="奇特">
			<exam article="《捕蛇者说》" ref="永州之野产异蛇。" />
		</sense>
		<sense tag="形意动" vernacular="以……为异">
			<exam article="《桃花源记》" ref="渔人甚异之。" />
		</sense>
		<sense tag="形" vernacular="特殊">
			<exam article="《劝学》" ref="君子生非异也，善假于物也。" />
		</sense>
		<sense tag="形" vernacular="优异；杰出">
			<exam article="《促织》" ref="无何，宰以卓异闻。" />
		</sense>
		<sense tag="形" vernacular="别的；另外的">
			<exam article="《某藷疏序》" ref="欲以树艺佐其急，且备异日也。" />
		</sense>
		<sense tag="名" vernacular="奇特的东西；特殊的本领；特别或意外的事">
			<exam article="《训俭示康》" ref="果、肴非远方珍异。" />
			<exam article="《促织》" ref="成述其异。" />
		</sense>
	</pron>
	<phrase value="异端">
		<sense value="不符合正统思想的教义、主张或言论" />
	</phrase>
	<phrase value="异日">
		<sense value="他日；将来" />
		<sense value="以往、从前" />
	</phrase>
</character>
