<character value="戚">
	<introduce>
		<pinyin value="qi1" writing="qī" />
		<bushou value="戈" />
		<bushoustroke value="4" />
		<stroke value="11" />
		<order value="横撇竖横横竖撇捺折撇捺" />
	</introduce>
	<pron value="qi">
		<sense tag="名" vernacular="古代一种像斧头的兵器" />
		<sense tag="动" vernacular="悲伤；忧伤">
			<exam article="《柳毅传》" ref="毅深为之戚。" />
			<exam article="《捕蛇者说》" ref="言之，貌若甚戚者。" />
			<exam article="《祭十二郎文》" ref="吾不可去，汝不肯来，恐旦暮死，而汝抱天涯之戚也。" />
		</sense>
		<sense tag="名" vernacular="亲戚；亲属">
			<exam article="《狱中杂记》" ref="富者就其戚属。贫则面语之。" />
		</sense>
	</pron>
	<phrase value="戚促">
		<sense value="窘迫；迫促" />
	</phrase>
	<phrase value="戚戚">
		<sense value="忧愁的样子" />
		<sense value="心动的样子" />
	</phrase>
</character>
