<character value="汤">
	<introduce>
		<pinyin value="tang1" writing="tāng" />
		<pinyin value="shang1" writing="shāng" />
		<bushou value="氵" />
		<bushoustroke value="3" />
		<stroke value="6" />
		<order value="捺捺横折撇撇" />
	</introduce>
	<pron value="tāng">
		<sense tag="名" vernacular="热水；开水">
			<exam article="《送东阳马生序》" ref="媵人持汤沃灌，以衾拥覆。" />
		</sense>
		<sense tag="名" vernacular="食物加水煮后的液汁">
			<exam article="《新嫁娘》" ref="三日入厨下，洗手作羹汤。" />
		</sense>
		<sense tag="名" vernacular="汤剂；用水煎服的中药">
			<exam article="《史记·偏鹊仓公列传》" ref="治病不以汤液。" />
		</sense>
		<sense tag="名" vernacular="人名">
			<exam article="《论积贮疏》" ref="世之有饥穰，天之行也，禹、汤被之矣。" />
		</sense>
	</pron>
	<pron value="tàng">
		<sense tag="动" vernacular="通“烫”">
			<exam article="《扁鹊见蔡桓公》" ref="疾在腠理，汤熨之所及也。" />
		</sense>
	</pron>
	<pron value="shāng">
		<sense vernacular="见“汤汤”" />
	</pron>
	<phrase value="汤池">
		<sense value="灌注沸水的护城河，喻称城防坚固" />
		<sense value="灌注温泉水的浴池" />
	</phrase>
	<phrase value="汤火">
		<sense value="沸水和烈火，比喻极其危险的情势" />
	</phrase>
	<phrase value="汤镬">
		<sense value="古代一种酷刑把人投入沸水中处死" />
	</phrase>
	<phrase value="汤汤">
		<sense value="shāngshāng水流浩大的样子" />
	</phrase>
</character>
