<character value="监">
	<introduce>
		<pinyin value="jian1" writing="jiān" />
		<pinyin value="jian4" writing="jiàn" />
		<bushou value="皿" />
		<bushoustroke value="5" />
		<stroke value="10" />
		<order value="竖竖撇横捺竖折竖竖横" />
	</introduce>
	<pron value="jiān">
		<sense tag="动" vernacular="从上往下看">
			<exam article="《诗经·大雅·皇矣》" ref="监观四方，求民之莫。" />
		</sense>
		<sense tag="动" vernacular="监视；监督">
			<exam article="《智取生辰纲》" ref="却监着那十一个军汉。" />
		</sense>
		<sense tag="动" vernacular="看守；守护">
			<exam article="《信陵君窃符救赵》" ref="为大梁夷门监者。" />
		</sense>
		<sense tag="名" vernacular="监狱；牢房">
			<exam article="《狱中杂记》" ref="求脱械居监外板屋，费亦数十金。" />
		</sense>
	</pron>
	<pron value="jiàn">
		<sense tag="名" vernacular="能照映出人和物形象的器具；镜子">
			<exam article="《新书·胎教》" ref="明监，所以照形也。" />
		</sense>
		<sense tag="动" vernacular="照看自己的形象">
			<exam article="《尚书·酒诰》" ref="人无于水监，当于民监。" />
		</sense>
		<sense tag="动" vernacular="借鉴；鉴戒">
			<exam article="《论语·八佾》" ref="周监于二代。" />
		</sense>
		<sense tag="名" vernacular="官署名" />
		<sense tag="名" vernacular="官名" />
	</pron>
	<phrase value="监修">
		<sense value="自北齐、隋以来，以大臣领修国史，谓之监修" />
	</phrase>
	<phrase value="监寐">
		<sense value="不脱衣冠而睡，犹言假寐" />
	</phrase>
</character>
