<character value="耸">
	<introduce>
		<pinyin value="song3" writing="sŏng" />
		<bushou value="耳" />
		<bushoustroke value="6" />
		<stroke value="10" />
		<order value="撇捺撇捺横竖竖横横横" />
	</introduce>
	<pron value="sǒng">
		<sense tag="形" vernacular="耳聋">
			<exam article="《广成颂》" ref="子野听耸，离朱目眩。" />
		</sense>
		<sense tag="动" vernacular="高起，高耸">
			<exam article="《种柳戏题》" ref="耸干会参天。" />
		</sense>
		<sense tag="动" vernacular="鼓励；劝勉">
			<exam article="《国语·楚语》" ref="为之耸善而抑恶焉。" />
		</sense>
		<sense vernacular="通“悚”">
			<exam article="《韩非子·内储说上》" ref="吏皆耸惧。" />
		</sense>
	</pron>
</character>
