<character value="肆">
	<introduce>
		<pinyin value="si4" writing="sì" />
		<bushou value="聿" />
		<bushoustroke value="6" />
		<stroke value="13" />
		<order value="横竖横横横折捺折横横横横竖" />
	</introduce>
	<pron value="sì">
		<sense tag="动" vernacular="陈列；陈设">
			<exam article="《杂诗》" ref="觞弦肆朝日，樽中酒不燥。" />
		</sense>
		<sense tag="名" vernacular="手工作坊">
			<exam article="《论语·子张》" ref="百工居肆以成其事。" />
		</sense>
		<sense tag="名" vernacular="商店；店铺">
			<exam article="《训俭示康》" ref="卿为清望官，奈何饮于酒肆？" />
		</sense>
		<sense tag="名" vernacular="集市；街市">
			<exam article="《马伶传》" ref="列兴化于东肆，华林于西肆。" />
		</sense>
		<sense tag="动" vernacular="放肆；放纵；任意">
			<exam article="《答韦中立论师道书》" ref="参之庄老以肆其端。" />
		</sense>
		<sense tag="动" vernacular="伸展；扩展">
			<exam article="《左传·僖公三年》" ref="（晋）又欲肆其西封。" />
		</sense>
	</pron>
</character>
