<character value="荐">
	<introduce>
		<pinyin value="jian4" writing="jiàn" />
		<bushou value="艹" />
		<bushoustroke value="3" />
		<stroke value="9" />
		<order value="横竖竖横撇竖折竖横" />
	</introduce>
	<pron value="jiàn">
		<sense tag="名" vernacular="兽类吃的草">
			<exam article="《庄子·齐物论》" ref="麋鹿食荐。" />
		</sense>
		<sense tag="名" vernacular="草席；草垫">
			<exam article="《九咏》" ref="茵荐兮兰席。" />
		</sense>
		<sense tag="动" vernacular="奉献；进献">
			<exam article="《论语·乡党》" ref="君赐腥，必熟而荐之。" />
		</sense>
		<sense tag="动" vernacular="祭奠；祭祀">
			<exam article="《窦娥冤》" ref="你去那受刑法尸骸上烈些纸钱，只当把你亡化的孩儿荐。" />
		</sense>
		<sense tag="动" vernacular="推荐；举荐">
			<exam article="《谭嗣同》" ref="君以学士徐公致靖荐，被征。" />
		</sense>
		<sense tag="副" vernacular="接连；频繁；屡次">
			<exam article="《国语·鲁语》" ref="饥馑荐降。" />
		</sense>
		<sense tag="动" vernacular="通“搢”，插">
			<exam article="《答韦中立论师道书》" ref="明日造朝，至外廷，荐笏言于卿士。" />
		</sense>
	</pron>
	<phrase value="荐享">
		<sense value="祭祀，进献祭品" />
		<sense value="喂，食" />
	</phrase>
</character>
