<character value="蒸">
	<introduce>
		<pinyin value="zheng1" writing="zhēng" />
		<bushou value="艹" />
		<bushoustroke value="3" />
		<stroke value="13" />
		<order value="横竖竖折竖折撇捺横捺捺捺捺" />
	</introduce>
	<pron value="zhēng">
		<sense tag="名" vernacular="细小的木柴">
			<exam article="《淮南子·主术训》" ref="冬伐薪蒸。" />
		</sense>
		<sense tag="动" vernacular="气体上升">
			<exam article="《后汉书·冯衍传》" ref="风兴云蒸，一龙一蛇。" />
		</sense>
		<sense tag="形" vernacular="通“烝”">
			<exam article="《与从弟君苗君胄书》" ref="济蒸人于涂炭。" />
		</sense>
	</pron>
	<phrase value="蒸黎">
		<sense value="百姓" />
	</phrase>
	<phrase value="蒸庶">
		<sense value="百姓" />
	</phrase>
	<phrase value="蒸蒸">
		<sense value="兴盛；上进" />
		<sense value="淳厚的样子" />
	</phrase>
</character>
