<character value="铨">
	<introduce>
		<pinyin value="quan2" writing="quán" />
		<bushou value="钅" />
		<bushoustroke value="5" />
		<stroke value="11" />
		<order value="撇横横横折撇捺横横竖横" />
	</introduce>
	<pron value="quán">
		<sense tag="动" vernacular="衡量；称量">
			<exam article="《国语·吴语》" ref="不智，……无以铨度天下之众寡。" />
		</sense>
		<sense tag="动" vernacular="选拔（人才），选授（官职）">
			<exam article="《记王忠肃公翱事》" ref="而翁长铨，迁我京职，则汝朝夕侍母。" />
		</sense>
	</pron>
	<phrase value="铨叙">
		<sense value="根据官吏的资绩，确定及升降等级" />
		<sense value="序次" />
	</phrase>
</character>
